algolab/__init__.py
algolab/abc_algo.py
algolab/service.py
algolab/apis/__init__.py
algolab/apis/abc_api.py
algolab/apis/consumer/__init__.py
algolab/apis/consumer/api.py
algolab/apis/crypto/__init__.py
algolab/apis/crypto/coingecko.py
algolab/price_listener/__init__.py
algolab/price_listener/listener.py
algolab/price_listener/service.py
algolab/tradables/__init__.py
algolab/tradables/abc_tradable.py
algolab/tradables/crypto.py
algolab-0.0.4.dist-info/LICENSE.md
algolab-0.0.4.dist-info/METADATA
algolab-0.0.4.dist-info/WHEEL
algolab-0.0.4.dist-info/top_level.txt
algolab-0.0.4.dist-info/RECORD
